{
  "db_name": "PostgreSQL",
  "query": "\n            INSERT INTO unit_owners (\n                id, unit_id, owner_id, ownership_percentage,\n                start_date, end_date, is_primary_contact,\n                created_at, updated_at\n            )\n            VALUES ($1, $2, $3, $4, $5, $6, $7, $8, $9)\n            RETURNING *\n            ",
  "describe": {
    "columns": [
      {
        "ordinal": 0,
        "name": "id",
        "type_info": "Uuid"
      },
      {
        "ordinal": 1,
        "name": "unit_id",
        "type_info": "Uuid"
      },
      {
        "ordinal": 2,
        "name": "owner_id",
        "type_info": "Uuid"
      },
      {
        "ordinal": 3,
        "name": "ownership_percentage",
        "type_info": "Float8"
      },
      {
        "ordinal": 4,
        "name": "start_date",
        "type_info": "Timestamptz"
      },
      {
        "ordinal": 5,
        "name": "end_date",
        "type_info": "Timestamptz"
      },
      {
        "ordinal": 6,
        "name": "is_primary_contact",
        "type_info": "Bool"
      },
      {
        "ordinal": 7,
        "name": "created_at",
        "type_info": "Timestamptz"
      },
      {
        "ordinal": 8,
        "name": "updated_at",
        "type_info": "Timestamptz"
      }
    ],
    "parameters": {
      "Left": [
        "Uuid",
        "Uuid",
        "Uuid",
        "Float8",
        "Timestamptz",
        "Timestamptz",
        "Bool",
        "Timestamptz",
        "Timestamptz"
      ]
    },
    "nullable": [
      false,
      false,
      false,
      false,
      false,
      true,
      false,
      false,
      false
    ]
  },
  "hash": "3bf6f4a6ac3962e772b444bfbf46f32a2f28cb47b7e2667a111a59f444fbe405"
}
