{
  "db_name": "PostgreSQL",
  "query": "\n            SELECT id, building_id, prm, provider::TEXT as provider, api_key_encrypted, refresh_token_encrypted,\n                   token_expires_at, sync_enabled, last_sync_at, created_at, updated_at\n            FROM linky_devices\n            WHERE building_id = $1\n            ",
  "describe": {
    "columns": [
      {
        "ordinal": 0,
        "name": "id",
        "type_info": "Uuid"
      },
      {
        "ordinal": 1,
        "name": "building_id",
        "type_info": "Uuid"
      },
      {
        "ordinal": 2,
        "name": "prm",
        "type_info": "Varchar"
      },
      {
        "ordinal": 3,
        "name": "provider",
        "type_info": "Text"
      },
      {
        "ordinal": 4,
        "name": "api_key_encrypted",
        "type_info": "Text"
      },
      {
        "ordinal": 5,
        "name": "refresh_token_encrypted",
        "type_info": "Text"
      },
      {
        "ordinal": 6,
        "name": "token_expires_at",
        "type_info": "Timestamptz"
      },
      {
        "ordinal": 7,
        "name": "sync_enabled",
        "type_info": "Bool"
      },
      {
        "ordinal": 8,
        "name": "last_sync_at",
        "type_info": "Timestamptz"
      },
      {
        "ordinal": 9,
        "name": "created_at",
        "type_info": "Timestamptz"
      },
      {
        "ordinal": 10,
        "name": "updated_at",
        "type_info": "Timestamptz"
      }
    ],
    "parameters": {
      "Left": [
        "Uuid"
      ]
    },
    "nullable": [
      false,
      false,
      false,
      null,
      false,
      true,
      true,
      false,
      true,
      false,
      false
    ]
  },
  "hash": "46624c9bfb6287b93d282eade652b8169449cead95126c581c0d73b56613843a"
}
